LICENSE
MANIFEST.in
README.md
setup.cfg
setup.py
trail/__init__.py
trail/__main__.py
trail/trail.py
trail.egg-info/PKG-INFO
trail.egg-info/SOURCES.txt
trail.egg-info/dependency_links.txt
trail.egg-info/entry_points.txt
trail.egg-info/top_level.txt