Metadata-Version: 1.1
Name: trail
Version: 0.1.0
Summary: Keep track of your thoughts.
Home-page: https://github.com/tolbot/trail
Author: tolbot
Author-email: eltolis@hotmail.com
License: UNKNOWN
Download-URL: https://github.com/tolbot/trail/archive/0.1.0.tar.gz
Keywords: todo,productivity,notes
Platform: UNKNOWN
